level1/level2/level3/countermod10.v
module countermod10 (
    input wire [3:0] data,
    input wire loadn,
    input wire clrn,
    input wire clk,
    input wire en,
    output reg [3:0] ones,
    output reg tc,
    output reg zero
);

initial begin
    tc = 0;
    zero = 0;
end

always @ (negedge clrn)
begin
    ones = 4'b0000;
    zero = 1'b1;
end

always @ (negedge loadn)
begin
    ones = data;
    zero = (ones == 4'b0000) ? 1'b1 : 1'b0;
end

always @ (posedge clk)
begin
    if (en) 
        case (ones)
            4'b1001: begin
                ones <= 4'b1000;
                tc <= 1'b0;
                zero <= 1'b0;
            end
            4'b1000: ones <= 4'b0111; // 8 -> 7
            4'b0111: ones <= 4'b0110; // 7 -> 6
            4'b0110: ones <= 4'b0101; // 6 -> 5
            4'b0101: ones <= 4'b0100; // 5 -> 4
            4'b0100: ones <= 4'b0011; // 4 -> 3
            4'b0011: ones <= 4'b0010; // 3 -> 2
            4'b0010: ones <= 4'b0001; // 2 -> 1
            4'b0001: begin 
                ones <= 4'b0000;
                tc <= 1'b1;
                zero <= 1'b1;
            end  // 1 -> 0
            4'b0000: begin
                ones <= 4'b1001;
                tc <= 1'b0;
                zero <= 1'b0;
            end // 0 -> 9
            default: ones <= 4'b0000;
        endcase
    else begin
        tc <= 0;

        if(!loadn)
            ones <= data;
        
        end
    end
endmodule

level1/level2/level3/countermod10_test.v
module countermod10_test();
reg [3:0] data;
reg loadn, clrn, clk, en;

wire [3:0] ones;
wire tc, zero;

countermod10 dut (data, loadn, clrn, clk, en, ones, tc, zero);

initial clk = 0;
always #10 clk = !clk;

initial begin
    assign loadn = 1;
    assign en = 0; 
    assign clrn = 1;
    assign data = 4'b0110;

    #5 assign loadn = 0;

    #10 assign loadn = 1;

    #5 assign en = 0; 

    // assign loadn = 1; 
    // assign en = 0; 
    // assign clrn = 1;
    // assign data = 4'b0110;
    // #5 assign loadn = 0;
    // #5 assign loadn = 1; 
    // #5 assign en = 1; 
    // #50 assign clrn = 0;
    // assign en = 0;

    #400 $finish;
end

initial begin
    $monitor("simtime = %g,data =%b, loadn =%b, clrn =%b, clk =%b, en =%b, ones =%b, tc =%b, zero =%b", $time,data, loadn, clrn, clk, en, ones, tc, zero);
    $dumpfile("countermod10.vcd");
    $dumpvars(0,countermod10_test);
end

endmodule

level1/level2/level3/countermod10.vcd
$date
	Fri Aug 27 18:12:14 2021
$end
$version
	Icarus Verilog
$end
$timescale
	1s
$end
$scope module countermod10_test $end
$var wire 1 ! zero $end
$var wire 1 " tc $end
$var wire 4 # ones [3:0] $end
$var reg 1 $ clk $end
$var reg 1 % clrn $end
$var reg 4 & data [3:0] $end
$var reg 1 ' en $end
$var reg 1 ( loadn $end
$scope module dut $end
$var wire 1 $ clk $end
$var wire 1 % clrn $end
$var wire 4 ) data [3:0] $end
$var wire 1 ' en $end
$var wire 1 ( loadn $end
$var reg 4 * ones [3:0] $end
$var reg 1 " tc $end
$var reg 1 ! zero $end
$upscope $end
$upscope $end
$enddefinitions $end
#0
$dumpvars
bx *
b110 )
1(
0'
b110 &
1%
0$
bx #
0"
0!
$end
#5
b110 #
b110 *
0(
#10
1(
1$
#15
1'
#20
0$
#30
b101 #
b101 *
1$
#40
0$
#50
b100 #
b100 *
1$
#60
0$
#70
b11 #
b11 *
1$
#80
0$
#90
b10 #
b10 *
1$
#100
0$
#110
b1 #
b1 *
1$
#120
0$
#130
1!
1"
b0 #
b0 *
1$
#140
0$
#150
0!
0"
b1001 #
b1001 *
1$
#160
0$
#170
b1000 #
b1000 *
1$
#180
0$
#190
b111 #
b111 *
1$
#200
0$
#210
b110 #
b110 *
1$
#220
0$
#230
b101 #
b101 *
1$
#240
0$
#250
b100 #
b100 *
1$
#260
0$
#270
b11 #
b11 *
1$
#280
0$
#290
b10 #
b10 *
1$
#300
0$
#310
b1 #
b1 *
1$
#320
0$
#330
1!
1"
b0 #
b0 *
1$
#340
0$
#350
0!
0"
b1001 #
b1001 *
1$
#360
0$
#370
b1000 #
b1000 *
1$
#380
0$
#390
b111 #
b111 *
1$
#400
0$
#410
b110 #
b110 *
1$
