level1/level2/level3/counter0_7.v
module counter0_7 (
    input wire clk,
    input wire clear,
    output reg out
);

reg [3:0]count; // Maintains the current count
reg is_counting = 0; // Maintains the state of the counter

initial begin // Defines initial values
    out <= 0;
    count <= 0;
end

always @(negedge clear) begin // When clear is deactivated, starts the counter.
    if (count == 3'd0) begin
        is_counting = 1;
    end
end

always @(posedge clear) begin // When clear is activated, stops the counter if count is at 7.
    if (count == 3'd7) begin
        is_counting = 0;
        count = 3'd0;
        out = 0;
    end
end

always @(posedge clk) begin // Counts up if the counter is active.
    if (is_counting && count < 3'd7) begin
        count <= count + 1;
    end

    if (count == 3'd3) begin
        out <= 1;
    end
end


endmodule

level1/level2/level3/counter0_7_test.v
module counter0_7_test();

reg clk;
reg clear;
wire out;

counter0_7 dut(clk, clear, out);

initial clk = 0;
always #5 clk = ~clk;

initial begin
    clear <= 1;

    #5 clear <= 0;

    #200 clear <= 1;

    #500 $finish;
end

initial begin
    $dumpfile("counter0_7.vcd");
    $dumpvars(0, counter0_7_test);
end

endmodule

level1/level2/level3/counter0_7.vcd
$date
	Fri Aug 27 11:04:32 2021
$end
$version
	Icarus Verilog
$end
$timescale
	1s
$end
$scope module counter0_7_test $end
$var wire 1 ! out $end
$var reg 1 " clear $end
$var reg 1 # clk $end
$scope module dut $end
$var wire 1 " clear $end
$var wire 1 # clk $end
$var reg 4 $ count [3:0] $end
$var reg 1 % is_counting $end
$var reg 1 ! out $end
$upscope $end
$upscope $end
$enddefinitions $end
#0
$dumpvars
0%
b0 $
0#
1"
0!
$end
#5
1%
0"
1#
#10
0#
#15
b1 $
1#
#20
0#
#25
b10 $
1#
#30
0#
#35
b11 $
1#
#40
0#
#45
1!
b100 $
1#
#50
0#
#55
b101 $
1#
#60
0#
#65
b110 $
1#
#70
0#
#75
b111 $
1#
#80
0#
#85
1#
#90
0#
#95
1#
#100
0#
#105
1#
#110
0#
#115
1#
#120
0#
#125
1#
#130
0#
#135
1#
#140
0#
#145
1#
#150
0#
#155
1#
#160
0#
#165
1#
#170
0#
#175
1#
#180
0#
#185
1#
#190
0#
#195
1#
#200
0#
#205
0!
b0 $
0%
1"
1#
