level1/level2/level3/countermod6.v
module countermod6 (
    input wire [3:0] data,
    input wire loadn,
    input wire clrn,
    input wire clk,
    input wire en,
    output reg [3:0] tens,
    output reg tc,
    output reg zero
);

initial begin
    tc = 0;
    zero = 0;
end

always @ (negedge clrn)
begin
    tens = 4'b0000;
end

always @ (negedge loadn)
begin
    tens <= data;
end

always @ (posedge clk)
begin
    if (en) 
        case (tens)
            4'b1001: tens <= 4'b1000; // 9 -> 8
            4'b1000: tens <= 4'b0111; // 8 -> 7
            4'b0111: tens <= 4'b0110; // 7 -> 6
            4'b0110: tens <= 4'b0101; // 6 -> 5
            4'b0101: tens <= 4'b0100; // 5 -> 4
            4'b0100: tens <= 4'b0011; // 4 -> 3
            4'b0011: tens <= 4'b0010; // 3 -> 2
            4'b0010: tens <= 4'b0001; // 2 -> 1
            4'b0001: begin 
                tens <= 4'b0000;
                tc <= 1'b1;
                zero <= 1'b1;
            end  // 1 -> 0
            4'b0000: begin
                tens <= 4'b0110;
                tc <= 1'b0;
                zero <= 1'b0;
            end // 0 -> 6
            default: tens <= 4'b0000;
        endcase
        else begin 
        tc <= 0;
        end
    end
    
endmodule

level1/level2/level3/countermod6_test.v
module countermod6_test();
reg [3:0] data;
reg loadn, clrn, clk, en;

wire [3:0] tens;
wire tc, zero;

countermod6 dut(data, loadn, clrn, clk, en, tens, tc, zero);

initial clk = 0;
always #10 clk = !clk;

initial begin
    $dumpfile("countermod6.vcd");
    $dumpvars(0,countermod6_test);
end

initial begin
    assign loadn = 1;
    assign en = 0; 
    assign clrn = 1;
    assign data = 4'b0110;

    #5 assign loadn = 0;

    #5 assign loadn = 1;

    #5 assign en = 1; 

    #400 $finish;
end

endmodule

level1/level2/level3/countermod6.vcd
$date
	Fri Aug 27 18:10:14 2021
$end
$version
	Icarus Verilog
$end
$timescale
	1s
$end
$scope module countermod6_test $end
$var wire 1 ! zero $end
$var wire 4 " tens [3:0] $end
$var wire 1 # tc $end
$var reg 1 $ clk $end
$var reg 1 % clrn $end
$var reg 4 & data [3:0] $end
$var reg 1 ' en $end
$var reg 1 ( loadn $end
$scope module dut $end
$var wire 1 $ clk $end
$var wire 1 % clrn $end
$var wire 4 ) data [3:0] $end
$var wire 1 ' en $end
$var wire 1 ( loadn $end
$var reg 1 # tc $end
$var reg 4 * tens [3:0] $end
$var reg 1 ! zero $end
$upscope $end
$upscope $end
$enddefinitions $end
#0
$dumpvars
bx *
b110 )
1(
0'
b110 &
1%
0$
0#
bx "
0!
$end
#5
b110 "
b110 *
0(
#10
1(
1$
#15
1'
#20
0$
#30
b101 "
b101 *
1$
#40
0$
#50
b100 "
b100 *
1$
#60
0$
#70
b11 "
b11 *
1$
#80
0$
#90
b10 "
b10 *
1$
#100
0$
#110
b1 "
b1 *
1$
#120
0$
#130
1!
1#
b0 "
b0 *
1$
#140
0$
#150
0!
0#
b110 "
b110 *
1$
#160
0$
#170
b101 "
b101 *
1$
#180
0$
#190
b100 "
b100 *
1$
#200
0$
#210
b11 "
b11 *
1$
#220
0$
#230
b10 "
b10 *
1$
#240
0$
#250
b1 "
b1 *
1$
#260
0$
#270
1!
1#
b0 "
b0 *
1$
#280
0$
#290
0!
0#
b110 "
b110 *
1$
#300
0$
#310
b101 "
b101 *
1$
#320
0$
#330
b100 "
b100 *
1$
#340
0$
#350
b11 "
b11 *
1$
#360
0$
#370
b10 "
b10 *
1$
#380
0$
#390
b1 "
b1 *
1$
#400
0$
#410
1!
1#
b0 "
b0 *
1$
