level1/level2/level3/mux2_1.v
module mux2_1 (
    input wire selector,
    input wire d0,
    input wire d1,
    output reg out
);
    always @(d0 or d1 or selector) begin
        if(selector)
        out= d1;
        else
        out= d0;
    end
endmodule

level1/level2/level3/mux2_1_test.v
module mux2_1_test();

reg selector;
reg d0;
reg d1;
wire out;

mux2_1 dut(selector, d0, d1, out);

always #10 selector =~ selector;

initial begin
    selector <= 0;
    d0<=1'b0;
    d1<=1'b0;
    #5d0=1'b0;
    #5d1=1'b0;
    #5d0=1'b1;
    #5d1=1'b0;
    #5d0=1'b1;
    #5d1=1'b1;
    #5d0=1'b0;
    #5d1=1'b1;
    #5d0=1'b0;
    #5d1=1'b0;
    #100 $finish;
end

initial begin
    $dumpfile("mux2_1.vcd");
    $dumpvars(0,mux2_1_test);
end

endmodule

level1/level2/level3/mux2_1.vcd
$date
	Fri Aug 27 11:08:12 2021
$end
$version
	Icarus Verilog
$end
$timescale
	1s
$end
$scope module mux2_1_test $end
$var wire 1 ! out $end
$var reg 1 " d0 $end
$var reg 1 # d1 $end
$var reg 1 $ selector $end
$scope module dut $end
$var wire 1 " d0 $end
$var wire 1 # d1 $end
$var wire 1 $ selector $end
$var reg 1 ! out $end
$upscope $end
$upscope $end
$enddefinitions $end
#0
$dumpvars
0$
0#
0"
0!
$end
#10
1$
#15
1"
#20
1!
0$
#30
1#
1$
#35
0"
#40
0!
0$
#50
0#
1$
#60
0$
#70
1$
#80
0$
#90
1$
#100
0$
#110
1$
#120
0$
#130
1$
#140
0$
#150
1$
