level1/level2/level3/mux2_1.v
module mux2_1 (
    input wire selector,
    input wire d0,
    input wire d1,
    output reg out
);
    always @(d0 or d1 or selector) begin
        if(selector)
        out= d1;
        else
        out= d0;
    end
endmodule

level1/level2/level3/counterdiv100.v
module counterdiv100(
    input wire clk,
    output wire clk_out
);

reg [6:0] count = 0;
reg reached100 = 0;
assign clk_out = reached100;

always @(posedge clk) begin
    count <= count + 1;

    if (count == 7'd99) begin
        reached100 <= 1;
        count <= 0;
end
else begin
    reached100 <= 0;
end
end

endmodule

level1/level2/level3/counter0_7.v
module counter0_7 (
    input wire clk,
    input wire clear,
    output reg out
);

reg [3:0]count; // Maintains the current count
reg is_counting = 0; // Maintains the state of the counter

initial begin // Defines initial values
    out <= 0;
    count <= 0;
end

always @(negedge clear) begin // When clear is deactivated, starts the counter.
    if (count == 3'd0) begin
        is_counting = 1;
    end
end

always @(posedge clear) begin // When clear is activated, stops the counter if count is at 7.
    if (count == 3'd7) begin
        is_counting = 0;
        count = 3'd0;
        out = 0;
    end
end

always @(posedge clk) begin // Counts up if the counter is active.
    if (is_counting && count < 3'd7) begin
        count <= count + 1;
    end

    if (count == 3'd3) begin
        out <= 1;
    end
end


endmodule

level1/level2/level3/encoder_dec_bcd.v
module encoder_dec_bcd(
    input [9:0] decimal,
    input enable,
    output reg [3:0] bcd,
    output reg loadn
);

initial begin
    loadn<=0;
end

always @ (decimal)
begin
    if (!enable) begin
        loadn<=1;
        case(decimal)
            10'b0000000001:bcd=4'b0000;
            10'b0000000010:bcd=4'b0001;
            10'b0000000100:bcd=4'b0010;
            10'b0000001000:bcd=4'b0011;
            10'b0000010000:bcd=4'b0100;
            10'b0000100000:bcd=4'b0101;
            10'b0001000000:bcd=4'b0110;
            10'b0010000000:bcd=4'b0111;
            10'b0100000000:bcd=4'b1000;
            10'b1000000000:bcd=4'b1001;

            default: begin
                loadn<=0;
            end
        endcase
    end
end

endmodule

level1/level2/encoder.v
`include "level3/encoder_dec_bcd.v"
`include "level3/counter0_7.v"
`include "level3/counterdiv100.v"
`include "level3/mux2_1.v"

module encoder(
    input wire [9:0] numpad,
    input wire enable,
    input wire clk,
    output wire [3:0] D,
    output wire loadn,
    output wire pgt_1Hz
);

    wire clr, mux_d0, mux_d1;

    encoder_dec_bcd dec_to_bcd(.decimal(numpad), .enable(enable), .bcd(D), .loadn(loadn));
    counter0_7 debouncer(.clk(clk), .clear(clr), .out(mux_d0));
    counterdiv100 div100(.clk(clk), .clk_out(mux_d1));
    mux2_1 mux(.selector(enable), .d0(mux_d0), .d1(mux_d1), .out(pgt_1Hz));

    assign loadn = clr;

endmodule

level1/level2/encoder_test.v
`include "encoder.v"
module encoder_test;
reg [9:0] numpad;
reg enable;
reg clk;
wire [3:0] D;
wire loadn;
wire pgt_1Hz;

encoder dut(numpad, enable, clk, D, loadn, pgt_1Hz);

initial clk = 0;
always #5 clk = ~clk;

initial begin
    enable <= 0;
    #5 numpad <= 4'd1;
    #2 numpad <= 4'dx;
    #5 numpad <= 4'd0;
    #2 numpad <= 4'dx;
    #5 numpad <= 4'd5;
    #2 numpad <= 4'dx;
    #100 enable <= 1;
    #1000 $finish;
end

initial begin
    $dumpfile("encoder.vcd");
    $dumpvars(0, encoder_test);
end

endmodule

level1/level2/encoder.vcd
$date
	Fri Aug 27 14:56:02 2021
$end
$version
	Icarus Verilog
$end
$timescale
	1s
$end
$scope module encoder_test $end
$var wire 1 ! loadn $end
$var wire 1 " pgt_1Hz $end
$var wire 4 # D [3:0] $end
$var reg 1 $ clk $end
$var reg 1 % enable $end
$var reg 10 & numpad [9:0] $end
$scope module dut $end
$var wire 1 $ clk $end
$var wire 1 ' clr $end
$var wire 1 % enable $end
$var wire 1 ! loadn $end
$var wire 10 ( numpad [9:0] $end
$var wire 1 " pgt_1Hz $end
$var wire 1 ) mux_d1 $end
$var wire 1 * mux_d0 $end
$var wire 4 + D [3:0] $end
$scope module debouncer $end
$var wire 1 ' clear $end
$var wire 1 $ clk $end
$var reg 4 , count [3:0] $end
$var reg 1 - is_counting $end
$var reg 1 * out $end
$upscope $end
$scope module dec_to_bcd $end
$var wire 10 . decimal [9:0] $end
$var wire 1 % enable $end
$var reg 4 / bcd [3:0] $end
$var reg 1 0 loadn $end
$upscope $end
$scope module div100 $end
$var wire 1 $ clk $end
$var wire 1 ) clk_out $end
$var reg 7 1 count [6:0] $end
$var reg 1 2 reached100 $end
$upscope $end
$scope module mux $end
$var wire 1 * d0 $end
$var wire 1 ) d1 $end
$var wire 1 % selector $end
$var reg 1 " out $end
$upscope $end
$upscope $end
$upscope $end
$enddefinitions $end
#0
$dumpvars
02
b0 1
00
bx /
bx .
0-
b0 ,
bx +
0*
0)
bx (
z'
bx &
0%
0$
bx #
0"
0!
$end
#5
1!
10
b0 #
b0 +
b0 /
b1 1
b1 &
b1 (
b1 .
1$
#7
0!
00
b0xxxx &
b0xxxx (
b0xxxx .
#10
0$
#12
0!
00
b0 &
b0 (
b0 .
#14
0!
00
b0xxxx &
b0xxxx (
b0xxxx .
#15
b10 1
1$
#19
0!
00
b101 &
b101 (
b101 .
#20
0$
#21
0!
00
b0xxxx &
b0xxxx (
b0xxxx .
#25
b11 1
1$
#30
0$
#35
b100 1
1$
#40
0$
#45
b101 1
1$
#50
0$
#55
b110 1
1$
#60
0$
#65
b111 1
1$
#70
0$
#75
b1000 1
1$
#80
0$
#85
b1001 1
1$
#90
0$
#95
b1010 1
1$
#100
0$
#105
b1011 1
1$
#110
0$
#115
b1100 1
1$
#120
0$
#121
1%
#125
b1101 1
1$
#130
0$
#135
b1110 1
1$
#140
0$
#145
b1111 1
1$
#150
0$
#155
b10000 1
1$
#160
0$
#165
b10001 1
1$
#170
0$
#175
b10010 1
1$
#180
0$
#185
b10011 1
1$
#190
0$
#195
b10100 1
1$
#200
0$
#205
b10101 1
1$
#210
0$
#215
b10110 1
1$
#220
0$
#225
b10111 1
1$
#230
0$
#235
b11000 1
1$
#240
0$
#245
b11001 1
1$
#250
0$
#255
b11010 1
1$
#260
0$
#265
b11011 1
1$
#270
0$
#275
b11100 1
1$
#280
0$
#285
b11101 1
1$
#290
0$
#295
b11110 1
1$
#300
0$
#305
b11111 1
1$
#310
0$
#315
b100000 1
1$
#320
0$
#325
b100001 1
1$
#330
0$
#335
b100010 1
1$
#340
0$
#345
b100011 1
1$
#350
0$
#355
b100100 1
1$
#360
0$
#365
b100101 1
1$
#370
0$
#375
b100110 1
1$
#380
0$
#385
b100111 1
1$
#390
0$
#395
b101000 1
1$
#400
0$
#405
b101001 1
1$
#410
0$
#415
b101010 1
1$
#420
0$
#425
b101011 1
1$
#430
0$
#435
b101100 1
1$
#440
0$
#445
b101101 1
1$
#450
0$
#455
b101110 1
1$
#460
0$
#465
b101111 1
1$
#470
0$
#475
b110000 1
1$
#480
0$
#485
b110001 1
1$
#490
0$
#495
b110010 1
1$
#500
0$
#505
b110011 1
1$
#510
0$
#515
b110100 1
1$
#520
0$
#525
b110101 1
1$
#530
0$
#535
b110110 1
1$
#540
0$
#545
b110111 1
1$
#550
0$
#555
b111000 1
1$
#560
0$
#565
b111001 1
1$
#570
0$
#575
b111010 1
1$
#580
0$
#585
b111011 1
1$
#590
0$
#595
b111100 1
1$
#600
0$
#605
b111101 1
1$
#610
0$
#615
b111110 1
1$
#620
0$
#625
b111111 1
1$
#630
0$
#635
b1000000 1
1$
#640
0$
#645
b1000001 1
1$
#650
0$
#655
b1000010 1
1$
#660
0$
#665
b1000011 1
1$
#670
0$
#675
b1000100 1
1$
#680
0$
#685
b1000101 1
1$
#690
0$
#695
b1000110 1
1$
#700
0$
#705
b1000111 1
1$
#710
0$
#715
b1001000 1
1$
#720
0$
#725
b1001001 1
1$
#730
0$
#735
b1001010 1
1$
#740
0$
#745
b1001011 1
1$
#750
0$
#755
b1001100 1
1$
#760
0$
#765
b1001101 1
1$
#770
0$
#775
b1001110 1
1$
#780
0$
#785
b1001111 1
1$
#790
0$
#795
b1010000 1
1$
#800
0$
#805
b1010001 1
1$
#810
0$
#815
b1010010 1
1$
#820
0$
#825
b1010011 1
1$
#830
0$
#835
b1010100 1
1$
#840
0$
#845
b1010101 1
1$
#850
0$
#855
b1010110 1
1$
#860
0$
#865
b1010111 1
1$
#870
0$
#875
b1011000 1
1$
#880
0$
#885
b1011001 1
1$
#890
0$
#895
b1011010 1
1$
#900
0$
#905
b1011011 1
1$
#910
0$
#915
b1011100 1
1$
#920
0$
#925
b1011101 1
1$
#930
0$
#935
b1011110 1
1$
#940
0$
#945
b1011111 1
1$
#950
0$
#955
b1100000 1
1$
#960
0$
#965
b1100001 1
1$
#970
0$
#975
b1100010 1
1$
#980
0$
#985
b1100011 1
1$
#990
0$
#995
1"
1)
12
b0 1
1$
#1000
0$
#1005
0"
0)
02
b1 1
1$
#1010
0$
#1015
b10 1
1$
#1020
0$
#1025
b11 1
1$
#1030
0$
#1035
b100 1
1$
#1040
0$
#1045
b101 1
1$
#1050
0$
#1055
b110 1
1$
#1060
0$
#1065
b111 1
1$
#1070
0$
#1075
b1000 1
1$
#1080
0$
#1085
b1001 1
1$
#1090
0$
#1095
b1010 1
1$
#1100
0$
#1105
b1011 1
1$
#1110
0$
#1115
b1100 1
1$
