level1/level2/level3/countermod10.v
module countermod10 (
    input wire [3:0] data,
    input wire loadn,
    input wire clrn,
    input wire clk,
    input wire en,
    output wire [3:0] ones,
    output wire tc,
    output wire zero
);

    reg [ 3: 0 ] cur_state;
    assign ones = cur_state; 

    assign zero = (cur_state == 0) ? 1 : 0;
    assign tc = ((cur_state == 0) & en) ? 1 : 0;

    always @(posedge clk)
    begin: COUNTER
        if (en) begin
            if (cur_state == 4'b0000) begin
                cur_state <= 4'd9;
                //tc <= 1;
            end
            else begin
                cur_state <= cur_state - 1;
                //tc <= 0;
            end
        end
        else begin
            if (!loadn) begin
                cur_state <= data;
            end
        end
    end

    always @(negedge clrn) begin
        if (!clrn) begin
            cur_state <= 4'b0000;
            //tc <= 1;
        end
    end

endmodule

level1/level2/level3/countermod6.v
module countermod6 (
    input wire [3:0] data,
    input wire loadn,
    input wire clrn,
    input wire clk,
    input wire en,
    output wire [3:0] tens,
    output wire tc,
    output wire zero
);

reg [ 3: 0 ] cur_state;
    assign tens = cur_state; 

    assign zero = (cur_state == 0) ? 1 : 0;
    assign tc = ((cur_state == 0) & en) ? 1 : 0;

    always @(posedge clk)
    begin: COUNTER
        if (en) begin
            if (cur_state == 4'b0000) begin
                cur_state <= 4'd5;
                //tc <= 1;
            end
            else begin
                cur_state <= cur_state - 1;
                //tc <= 0;
            end
        end
        else begin
            if (!loadn) begin
                cur_state <= data;
            end
        end
    end

    always @(negedge clrn) begin
        if (!clrn) begin
            cur_state <= 4'b0000;
            //tc <= 1;
        end
    end

endmodule

level1/level2/timer.v
`include "level2/level3/countermod10.v"
`include "level2/level3/countermod6.v"
// for local testing
//`include "level3/countermod10.v"
//`include "level3/countermod6.v"

module timer(output wire[3:0] minutes, tens_secs, secs,
             output wire      timer_done,
             input  wire[3:0] digit,
             input  wire      clearn, enable, loadn, CLK);  // 1Hz clock
             // the timer must be disabled by the magnetron_control
             // block when the timer gets done

    wire tc1;
    wire zero1;

    countermod10 seconds_counter(digit, loadn, clearn, CLK, enable, secs, tc1, zero1);

    wire tc2;
    wire zero2;

    countermod6 tens_secs_counter(secs, loadn, clearn, CLK, tc1, tens_secs, tc2, zero2);

    wire tc3;
    wire zero3;

    countermod10 minutes_counter(tens_secs, loadn, clearn, CLK, tc2, minutes, tc3, zero3);


    assign timer_done = (zero1) & (zero2) & (zero3);  // the zero signal

    // if loadn is LOW, the timer is in load mode and will only receive
    // clock posedges for loading a digit. If loadn is HIGH, the timer is
    // in count mode and will receive a clock posedge signal every second
    

endmodule

level1/level2/timer_tb.v
`timescale 1s/1ms
module timer_tb();

    wire[3:0] minutes_tb, tens_secs_tb, secs_tb;
    wire timer_done_tb;
    reg [3:0]  digit_tb;
    reg clearn_tb, enable_tb, loadn_tb, CLK_tb;

    timer DUT (minutes_tb, tens_secs_tb, secs_tb, timer_done_tb,
                             digit_tb, clearn_tb, enable_tb, loadn_tb, CLK_tb);


    initial begin
        $dumpfile("timer_tb.vcd");
        $dumpvars(0, timer_tb);
        CLK_tb  = 1'b0;
        clearn_tb = 1'b1; 
        enable_tb = 1'b1; 
        loadn_tb  = 1'b0;
    end

    always begin
        #1 CLK_tb = loadn_tb? ~CLK_tb : CLK_tb;
    end

    initial begin    

        digit_tb =  2;   #0.04;
        CLK_tb = 1'b1;   #0.01;
        CLK_tb = 1'b0;   #0.95;

        digit_tb =  1;   #0.04;
        CLK_tb = 1'b1;   #0.01;
        CLK_tb = 1'b0;   #0.95;

        digit_tb =  7;   #0.04;
        CLK_tb = 1'b1;   #0.01;
        CLK_tb = 1'b0;   #0.95;

        digit_tb =  9;   #0.04;
        CLK_tb = 1'b1;   #0.01;
        CLK_tb = 1'b0;   #0.95;

        loadn_tb = 1;     #1000;

        $display("Successful");
        $finish();
    end

endmodule

level1/level2/timer_tb.vcd
$date
	Fri Aug 27 21:30:29 2021
$end
$version
	Icarus Verilog
$end
$timescale
	1ms
$end
$scope module timer_tb $end
$var wire 1 ! timer_done_tb $end
$var wire 4 " tens_secs_tb [3:0] $end
$var wire 4 # secs_tb [3:0] $end
$var wire 4 $ minutes_tb [3:0] $end
$var reg 1 % CLK_tb $end
$var reg 1 & clearn_tb $end
$var reg 4 ' digit_tb [3:0] $end
$var reg 1 ( enable_tb $end
$var reg 1 ) loadn_tb $end
$scope module DUT $end
$var wire 1 % CLK $end
$var wire 1 & clearn $end
$var wire 4 * digit [3:0] $end
$var wire 1 ( enable $end
$var wire 1 ) loadn $end
$var wire 1 ! timer_done $end
$var wire 1 + zero3 $end
$var wire 1 , zero2 $end
$var wire 1 - zero1 $end
$var wire 4 . tens_secs [3:0] $end
$var wire 1 / tc3 $end
$var wire 1 0 tc2 $end
$var wire 1 1 tc1 $end
$var wire 4 2 secs [3:0] $end
$var wire 4 3 minutes [3:0] $end
$scope module minutes_counter $end
$var wire 1 % clk $end
$var wire 1 & clrn $end
$var wire 1 ) loadn $end
$var wire 4 4 ones [3:0] $end
$var wire 1 + zero $end
$var wire 1 / tc $end
$var wire 1 0 en $end
$var wire 4 5 data [3:0] $end
$var reg 4 6 cur_state [3:0] $end
$scope begin COUNTER $end
$upscope $end
$upscope $end
$scope module seconds_counter $end
$var wire 1 % clk $end
$var wire 1 & clrn $end
$var wire 4 7 data [3:0] $end
$var wire 1 ( en $end
$var wire 1 ) loadn $end
$var wire 4 8 ones [3:0] $end
$var wire 1 - zero $end
$var wire 1 1 tc $end
$var reg 4 9 cur_state [3:0] $end
$scope begin COUNTER $end
$upscope $end
$upscope $end
$scope module tens_secs_counter $end
$var wire 1 % clk $end
$var wire 1 & clrn $end
$var wire 4 : data [3:0] $end
$var wire 1 1 en $end
$var wire 1 ) loadn $end
$var wire 4 ; tens [3:0] $end
$var wire 1 , zero $end
$var wire 1 0 tc $end
$var reg 4 < cur_state [3:0] $end
$scope begin COUNTER $end
$upscope $end
$upscope $end
$upscope $end
$upscope $end
$enddefinitions $end
#0
$dumpvars
bx <
bx ;
bx :
bx 9
bx 8
bx 7
bx 6
bx 5
bx 4
bx 3
bx 2
01
00
0/
bx .
x-
x,
x+
bx *
0)
0(
bx '
1&
0%
bx $
bx #
bx "
x!
$end
#500
1!
1-
1,
1+
b0 #
b0 2
b0 8
b0 :
b0 9
b0 "
b0 .
b0 5
b0 ;
b0 <
b0 $
b0 3
b0 4
b0 6
0&
#1000
1&
#1500
b10 '
b10 *
b10 7
#1540
0!
0-
b10 #
b10 2
b10 8
b10 :
b10 9
1%
#1550
0%
#2500
b1 '
b1 *
b1 7
#2540
0,
b10 "
b10 .
b10 5
b10 ;
b10 <
b1 #
b1 2
b1 8
b1 :
b1 9
1%
#2550
0%
#3500
b111 '
b111 *
b111 7
#3540
0+
b10 $
b10 3
b10 4
b10 6
b1 "
b1 .
b1 5
b1 ;
b1 <
b111 #
b111 2
b111 8
b111 :
b111 9
1%
#3550
0%
#4500
b1001 '
b1001 *
b1001 7
#4540
b1 $
b1 3
b1 4
b1 6
b111 "
b111 .
b111 5
b111 ;
b111 <
b1001 #
b1001 2
b1001 8
b1001 :
b1001 9
1%
#4550
0%
#5500
1)
1(
#6000
b1000 #
b1000 2
b1000 8
b1000 :
b1000 9
1%
#7000
0%
#8000
b111 #
b111 2
b111 8
b111 :
b111 9
1%
#9000
0%
#10000
b110 #
b110 2
b110 8
b110 :
b110 9
1%
#11000
0%
#12000
b101 #
b101 2
b101 8
b101 :
b101 9
1%
#13000
0%
#14000
b100 #
b100 2
b100 8
b100 :
b100 9
1%
#15000
0%
#16000
b11 #
b11 2
b11 8
b11 :
b11 9
1%
#17000
0%
#18000
b10 #
b10 2
b10 8
b10 :
b10 9
1%
#19000
0%
#20000
b1 #
b1 2
b1 8
b1 :
b1 9
1%
#21000
0%
#22000
11
1-
b0 #
b0 2
b0 8
b0 :
b0 9
1%
#23000
0%
#24000
01
0-
b110 "
b110 .
b110 5
b110 ;
b110 <
b1001 #
b1001 2
b1001 8
b1001 :
b1001 9
1%
#25000
0%
#26000
b1000 #
b1000 2
b1000 8
b1000 :
b1000 9
1%
#27000
0%
#28000
b111 #
b111 2
b111 8
b111 :
b111 9
1%
#29000
0%
#30000
b110 #
b110 2
b110 8
b110 :
b110 9
1%
#31000
0%
#32000
b101 #
b101 2
b101 8
b101 :
b101 9
1%
#33000
0%
#34000
b100 #
b100 2
b100 8
b100 :
b100 9
1%
#35000
0%
#36000
b11 #
b11 2
b11 8
b11 :
b11 9
1%
#37000
0%
#38000
b10 #
b10 2
b10 8
b10 :
b10 9
1%
#39000
0%
#40000
b1 #
b1 2
b1 8
b1 :
b1 9
1%
#41000
0%
#42000
11
1-
b0 #
b0 2
b0 8
b0 :
b0 9
1%
#43000
0%
#44000
01
0-
b101 "
b101 .
b101 5
b101 ;
b101 <
b1001 #
b1001 2
b1001 8
b1001 :
b1001 9
1%
#45000
0%
#46000
b1000 #
b1000 2
b1000 8
b1000 :
b1000 9
1%
#47000
0%
#48000
b111 #
b111 2
b111 8
b111 :
b111 9
1%
#49000
0%
#50000
b110 #
b110 2
b110 8
b110 :
b110 9
1%
#51000
0%
#52000
b101 #
b101 2
b101 8
b101 :
b101 9
1%
#53000
0%
#54000
b100 #
b100 2
b100 8
b100 :
b100 9
1%
#55000
0%
#56000
b11 #
b11 2
b11 8
b11 :
b11 9
1%
#57000
0%
#58000
b10 #
b10 2
b10 8
b10 :
b10 9
1%
#59000
0%
#60000
b1 #
b1 2
b1 8
b1 :
b1 9
1%
#61000
0%
#62000
11
1-
b0 #
b0 2
b0 8
b0 :
b0 9
1%
#63000
0%
#64000
01
0-
b100 "
b100 .
b100 5
b100 ;
b100 <
b1001 #
b1001 2
b1001 8
b1001 :
b1001 9
1%
#65000
0%
#66000
b1000 #
b1000 2
b1000 8
b1000 :
b1000 9
1%
#67000
0%
#68000
b111 #
b111 2
b111 8
b111 :
b111 9
1%
#69000
0%
#70000
b110 #
b110 2
b110 8
b110 :
b110 9
1%
#71000
0%
#72000
b101 #
b101 2
b101 8
b101 :
b101 9
1%
#73000
0%
#74000
b100 #
b100 2
b100 8
b100 :
b100 9
1%
#75000
0%
#76000
b11 #
b11 2
b11 8
b11 :
b11 9
1%
#77000
0%
#78000
b10 #
b10 2
b10 8
b10 :
b10 9
1%
#79000
0%
#80000
b1 #
b1 2
b1 8
b1 :
b1 9
1%
#81000
0%
#82000
11
1-
b0 #
b0 2
b0 8
b0 :
b0 9
1%
#83000
0%
#84000
01
0-
b11 "
b11 .
b11 5
b11 ;
b11 <
b1001 #
b1001 2
b1001 8
b1001 :
b1001 9
1%
#85000
0%
#86000
b1000 #
b1000 2
b1000 8
b1000 :
b1000 9
1%
#87000
0%
#88000
b111 #
b111 2
b111 8
b111 :
b111 9
1%
#89000
0%
#90000
b110 #
b110 2
b110 8
b110 :
b110 9
1%
#91000
0%
#92000
b101 #
b101 2
b101 8
b101 :
b101 9
1%
#93000
0%
#94000
b100 #
b100 2
b100 8
b100 :
b100 9
1%
#95000
0%
#96000
b11 #
b11 2
b11 8
b11 :
b11 9
1%
#97000
0%
#98000
b10 #
b10 2
b10 8
b10 :
b10 9
1%
#99000
0%
#100000
b1 #
b1 2
b1 8
b1 :
b1 9
1%
#101000
0%
#102000
11
1-
b0 #
b0 2
b0 8
b0 :
b0 9
1%
#103000
0%
#104000
01
0-
b10 "
b10 .
b10 5
b10 ;
b10 <
b1001 #
b1001 2
b1001 8
b1001 :
b1001 9
1%
#105000
0%
#106000
b1000 #
b1000 2
b1000 8
b1000 :
b1000 9
1%
#107000
0%
#108000
b111 #
b111 2
b111 8
b111 :
b111 9
1%
#109000
0%
#110000
b110 #
b110 2
b110 8
b110 :
b110 9
1%
#111000
0%
#112000
b101 #
b101 2
b101 8
b101 :
b101 9
1%
#113000
0%
#114000
b100 #
b100 2
b100 8
b100 :
b100 9
1%
#115000
0%
#116000
b11 #
b11 2
b11 8
b11 :
b11 9
1%
#117000
0%
#118000
b10 #
b10 2
b10 8
b10 :
b10 9
1%
#119000
0%
#120000
b1 #
b1 2
b1 8
b1 :
b1 9
1%
#121000
0%
#122000
11
1-
b0 #
b0 2
b0 8
b0 :
b0 9
1%
#123000
0%
#124000
01
0-
b1 "
b1 .
b1 5
b1 ;
b1 <
b1001 #
b1001 2
b1001 8
b1001 :
b1001 9
1%
#125000
0%
#126000
b1000 #
b1000 2
b1000 8
b1000 :
b1000 9
1%
#127000
0%
#128000
b111 #
b111 2
b111 8
b111 :
b111 9
1%
#129000
0%
#130000
b110 #
b110 2
b110 8
b110 :
b110 9
1%
#131000
0%
#132000
b101 #
b101 2
b101 8
b101 :
b101 9
1%
#133000
0%
#134000
b100 #
b100 2
b100 8
b100 :
b100 9
1%
#135000
0%
#136000
b11 #
b11 2
b11 8
b11 :
b11 9
1%
#137000
0%
#138000
b10 #
b10 2
b10 8
b10 :
b10 9
1%
#139000
0%
#140000
b1 #
b1 2
b1 8
b1 :
b1 9
1%
#141000
0%
#142000
11
1-
b0 #
b0 2
b0 8
b0 :
b0 9
1%
#143000
0%
#144000
00
01
1,
0-
b0 "
b0 .
b0 5
b0 ;
b0 <
b1001 #
b1001 2
b1001 8
b1001 :
b1001 9
1%
#145000
0%
#146000
b1000 #
b1000 2
b1000 8
b1000 :
b1000 9
1%
#147000
0%
#148000
b111 #
b111 2
b111 8
b111 :
b111 9
1%
#149000
0%
#150000
b110 #
b110 2
b110 8
b110 :
b110 9
1%
#151000
0%
#152000
b101 #
b101 2
b101 8
b101 :
b101 9
1%
#153000
0%
#154000
b100 #
b100 2
b100 8
b100 :
b100 9
1%
#155000
0%
#156000
b11 #
b11 2
b11 8
b11 :
b11 9
1%
#157000
0%
#158000
b10 #
b10 2
b10 8
b10 :
b10 9
1%
#159000
0%
#160000
b1 #
b1 2
b1 8
b1 :
b1 9
1%
#161000
0%
#162000
10
11
1-
b0 #
b0 2
b0 8
b0 :
b0 9
1%
#163000
0%
#164000
0/
00
01
1+
0,
0-
b0 $
b0 3
b0 4
b0 6
b101 "
b101 .
b101 5
b101 ;
b101 <
b1001 #
b1001 2
b1001 8
b1001 :
b1001 9
1%
#165000
0%
#166000
b1000 #
b1000 2
b1000 8
b1000 :
b1000 9
1%
#167000
0%
#168000
b111 #
b111 2
b111 8
b111 :
b111 9
1%
#169000
0%
#170000
b110 #
b110 2
b110 8
b110 :
b110 9
1%
#171000
0%
#172000
b101 #
b101 2
b101 8
b101 :
b101 9
1%
#173000
0%
#174000
b100 #
b100 2
b100 8
b100 :
b100 9
1%
#175000
0%
#176000
b11 #
b11 2
b11 8
b11 :
b11 9
1%
#177000
0%
#178000
b10 #
b10 2
b10 8
b10 :
b10 9
1%
#179000
0%
#180000
b1 #
b1 2
b1 8
b1 :
b1 9
1%
#181000
0%
#182000
11
1-
b0 #
b0 2
b0 8
b0 :
b0 9
1%
#183000
0%
#184000
01
0-
b100 "
b100 .
b100 5
b100 ;
b100 <
b1001 #
b1001 2
b1001 8
b1001 :
b1001 9
1%
#185000
0%
#186000
b1000 #
b1000 2
b1000 8
b1000 :
b1000 9
1%
#187000
0%
#188000
b111 #
b111 2
b111 8
b111 :
b111 9
1%
#189000
0%
#190000
b110 #
b110 2
b110 8
b110 :
b110 9
1%
#191000
0%
#192000
b101 #
b101 2
b101 8
b101 :
b101 9
1%
#193000
0%
#194000
b100 #
b100 2
b100 8
b100 :
b100 9
1%
#195000
0%
#196000
b11 #
b11 2
b11 8
b11 :
b11 9
1%
#197000
0%
#198000
b10 #
b10 2
b10 8
b10 :
b10 9
1%
#199000
0%
#200000
b1 #
b1 2
b1 8
b1 :
b1 9
1%
#201000
0%
#202000
11
1-
b0 #
b0 2
b0 8
b0 :
b0 9
1%
#203000
0%
#204000
01
0-
b11 "
b11 .
b11 5
b11 ;
b11 <
b1001 #
b1001 2
b1001 8
b1001 :
b1001 9
1%
#205000
0%
#206000
b1000 #
b1000 2
b1000 8
b1000 :
b1000 9
1%
#207000
0%
#208000
b111 #
b111 2
b111 8
b111 :
b111 9
1%
#209000
0%
#210000
b110 #
b110 2
b110 8
b110 :
b110 9
1%
#211000
0%
#212000
b101 #
b101 2
b101 8
b101 :
b101 9
1%
#213000
0%
#214000
b100 #
b100 2
b100 8
b100 :
b100 9
1%
#215000
0%
#216000
b11 #
b11 2
b11 8
b11 :
b11 9
1%
#217000
0%
#218000
b10 #
b10 2
b10 8
b10 :
b10 9
1%
#219000
0%
#220000
b1 #
b1 2
b1 8
b1 :
b1 9
1%
#221000
0%
#222000
11
1-
b0 #
b0 2
b0 8
b0 :
b0 9
1%
#223000
0%
#224000
01
0-
b10 "
b10 .
b10 5
b10 ;
b10 <
b1001 #
b1001 2
b1001 8
b1001 :
b1001 9
1%
#225000
0%
#226000
b1000 #
b1000 2
b1000 8
b1000 :
b1000 9
1%
#227000
0%
#228000
b111 #
b111 2
b111 8
b111 :
b111 9
1%
#229000
0%
#230000
b110 #
b110 2
b110 8
b110 :
b110 9
1%
#231000
0%
#232000
b101 #
b101 2
b101 8
b101 :
b101 9
1%
#233000
0%
#234000
b100 #
b100 2
b100 8
b100 :
b100 9
1%
#235000
0%
#236000
b11 #
b11 2
b11 8
b11 :
b11 9
1%
#237000
0%
#238000
b10 #
b10 2
b10 8
b10 :
b10 9
1%
#239000
0%
#240000
b1 #
b1 2
b1 8
b1 :
b1 9
1%
#241000
0%
#242000
11
1-
b0 #
b0 2
b0 8
b0 :
b0 9
1%
#243000
0%
#244000
01
0-
b1 "
b1 .
b1 5
b1 ;
b1 <
b1001 #
b1001 2
b1001 8
b1001 :
b1001 9
1%
#245000
0%
#246000
b1000 #
b1000 2
b1000 8
b1000 :
b1000 9
1%
#247000
0%
#248000
b111 #
b111 2
b111 8
b111 :
b111 9
1%
#249000
0%
#250000
b110 #
b110 2
b110 8
b110 :
b110 9
1%
#251000
0%
#252000
b101 #
b101 2
b101 8
b101 :
b101 9
1%
#253000
0%
#254000
b100 #
b100 2
b100 8
b100 :
b100 9
1%
#255000
0%
#256000
b11 #
b11 2
b11 8
b11 :
b11 9
1%
#257000
0%
#258000
b10 #
b10 2
b10 8
b10 :
b10 9
1%
#259000
0%
#260000
b1 #
b1 2
b1 8
b1 :
b1 9
1%
#261000
0%
#262000
11
1-
b0 #
b0 2
b0 8
b0 :
b0 9
1%
#263000
0%
#264000
0/
00
01
1,
0-
b0 "
b0 .
b0 5
b0 ;
b0 <
b1001 #
b1001 2
b1001 8
b1001 :
b1001 9
1%
#265000
0%
#266000
b1000 #
b1000 2
b1000 8
b1000 :
b1000 9
1%
#267000
0%
#268000
b111 #
b111 2
b111 8
b111 :
b111 9
1%
#269000
0%
#270000
b110 #
b110 2
b110 8
b110 :
b110 9
1%
#271000
0%
#272000
b101 #
b101 2
b101 8
b101 :
b101 9
1%
#273000
0%
#274000
b100 #
b100 2
b100 8
b100 :
b100 9
1%
#275000
0%
#276000
b11 #
b11 2
b11 8
b11 :
b11 9
1%
#277000
0%
#278000
b10 #
b10 2
b10 8
b10 :
b10 9
1%
#279000
0%
#280000
b1 #
b1 2
b1 8
b1 :
b1 9
1%
#281000
0%
#282000
1/
10
1!
11
1-
b0 #
b0 2
b0 8
b0 :
b0 9
1%
#283000
0%
#284000
0!
0/
00
01
0+
0,
0-
b1001 $
b1001 3
b1001 4
b1001 6
b101 "
b101 .
b101 5
b101 ;
b101 <
b1001 #
b1001 2
b1001 8
b1001 :
b1001 9
1%
#285000
0%
#286000
b1000 #
b1000 2
b1000 8
b1000 :
b1000 9
1%
#287000
0%
#288000
b111 #
b111 2
b111 8
b111 :
b111 9
1%
#289000
0%
#290000
b110 #
b110 2
b110 8
b110 :
b110 9
1%
#291000
0%
#292000
b101 #
b101 2
b101 8
b101 :
b101 9
1%
#293000
0%
#294000
b100 #
b100 2
b100 8
b100 :
b100 9
1%
#295000
0%
#296000
b11 #
b11 2
b11 8
b11 :
b11 9
1%
#297000
0%
#298000
b10 #
b10 2
b10 8
b10 :
b10 9
1%
#299000
0%
#300000
b1 #
b1 2
b1 8
b1 :
b1 9
1%
#301000
0%
#302000
11
1-
b0 #
b0 2
b0 8
b0 :
b0 9
1%
#303000
0%
#304000
01
0-
b100 "
b100 .
b100 5
b100 ;
b100 <
b1001 #
b1001 2
b1001 8
b1001 :
b1001 9
1%
#305000
0%
#306000
b1000 #
b1000 2
b1000 8
b1000 :
b1000 9
1%
#307000
0%
#308000
b111 #
b111 2
b111 8
b111 :
b111 9
1%
#309000
0%
#310000
b110 #
b110 2
b110 8
b110 :
b110 9
1%
#311000
0%
#312000
b101 #
b101 2
b101 8
b101 :
b101 9
1%
#313000
0%
#314000
b100 #
b100 2
b100 8
b100 :
b100 9
1%
#315000
0%
#316000
b11 #
b11 2
b11 8
b11 :
b11 9
1%
#317000
0%
#318000
b10 #
b10 2
b10 8
b10 :
b10 9
1%
#319000
0%
#320000
b1 #
b1 2
b1 8
b1 :
b1 9
1%
#321000
0%
#322000
11
1-
b0 #
b0 2
b0 8
b0 :
b0 9
1%
#323000
0%
#324000
01
0-
b11 "
b11 .
b11 5
b11 ;
b11 <
b1001 #
b1001 2
b1001 8
b1001 :
b1001 9
1%
#325000
0%
#326000
b1000 #
b1000 2
b1000 8
b1000 :
b1000 9
1%
#327000
0%
#328000
b111 #
b111 2
b111 8
b111 :
b111 9
1%
#329000
0%
#330000
b110 #
b110 2
b110 8
b110 :
b110 9
1%
#331000
0%
#332000
b101 #
b101 2
b101 8
b101 :
b101 9
1%
#333000
0%
#334000
b100 #
b100 2
b100 8
b100 :
b100 9
1%
#335000
0%
#336000
b11 #
b11 2
b11 8
b11 :
b11 9
1%
#337000
0%
#338000
b10 #
b10 2
b10 8
b10 :
b10 9
1%
#339000
0%
#340000
b1 #
b1 2
b1 8
b1 :
b1 9
1%
#341000
0%
#342000
11
1-
b0 #
b0 2
b0 8
b0 :
b0 9
1%
#343000
0%
#344000
01
0-
b10 "
b10 .
b10 5
b10 ;
b10 <
b1001 #
b1001 2
b1001 8
b1001 :
b1001 9
1%
#345000
0%
#346000
b1000 #
b1000 2
b1000 8
b1000 :
b1000 9
1%
#347000
0%
#348000
b111 #
b111 2
b111 8
b111 :
b111 9
1%
#349000
0%
#350000
b110 #
b110 2
b110 8
b110 :
b110 9
1%
#351000
0%
#352000
b101 #
b101 2
b101 8
b101 :
b101 9
1%
#353000
0%
#354000
b100 #
b100 2
b100 8
b100 :
b100 9
1%
#355000
0%
#356000
b11 #
b11 2
b11 8
b11 :
b11 9
1%
#357000
0%
#358000
b10 #
b10 2
b10 8
b10 :
b10 9
1%
#359000
0%
#360000
b1 #
b1 2
b1 8
b1 :
b1 9
1%
#361000
0%
#362000
11
1-
b0 #
b0 2
b0 8
b0 :
b0 9
1%
#363000
0%
#364000
01
0-
b1 "
b1 .
b1 5
b1 ;
b1 <
b1001 #
b1001 2
b1001 8
b1001 :
b1001 9
1%
#365000
0%
#366000
b1000 #
b1000 2
b1000 8
b1000 :
b1000 9
1%
#367000
0%
#368000
b111 #
b111 2
b111 8
b111 :
b111 9
1%
#369000
0%
#370000
b110 #
b110 2
b110 8
b110 :
b110 9
1%
#371000
0%
#372000
b101 #
b101 2
b101 8
b101 :
b101 9
1%
#373000
0%
#374000
b100 #
b100 2
b100 8
b100 :
b100 9
1%
#375000
0%
#376000
b11 #
b11 2
b11 8
b11 :
b11 9
1%
#377000
0%
#378000
b10 #
b10 2
b10 8
b10 :
b10 9
1%
#379000
0%
#380000
b1 #
b1 2
b1 8
b1 :
b1 9
1%
#381000
0%
#382000
11
1-
b0 #
b0 2
b0 8
b0 :
b0 9
1%
#383000
0%
#384000
00
01
1,
0-
b0 "
b0 .
b0 5
b0 ;
b0 <
b1001 #
b1001 2
b1001 8
b1001 :
b1001 9
1%
#385000
0%
#386000
b1000 #
b1000 2
b1000 8
b1000 :
b1000 9
1%
#387000
0%
#388000
b111 #
b111 2
b111 8
b111 :
b111 9
1%
#389000
0%
#390000
b110 #
b110 2
b110 8
b110 :
b110 9
1%
#391000
0%
#392000
b101 #
b101 2
b101 8
b101 :
b101 9
1%
#393000
0%
#394000
b100 #
b100 2
b100 8
b100 :
b100 9
1%
#395000
0%
#396000
b11 #
b11 2
b11 8
b11 :
b11 9
1%
#397000
0%
#398000
b10 #
b10 2
b10 8
b10 :
b10 9
1%
#399000
0%
#400000
b1 #
b1 2
b1 8
b1 :
b1 9
1%
#401000
0%
#402000
10
11
1-
b0 #
b0 2
b0 8
b0 :
b0 9
1%
#403000
0%
#404000
00
01
0,
0-
b1000 $
b1000 3
b1000 4
b1000 6
b101 "
b101 .
b101 5
b101 ;
b101 <
b1001 #
b1001 2
b1001 8
b1001 :
b1001 9
1%
#405000
0%
#406000
b1000 #
b1000 2
b1000 8
b1000 :
b1000 9
1%
#407000
0%
#408000
b111 #
b111 2
b111 8
b111 :
b111 9
1%
#409000
0%
#410000
b110 #
b110 2
b110 8
b110 :
b110 9
1%
#411000
0%
#412000
b101 #
b101 2
b101 8
b101 :
b101 9
1%
#413000
0%
#414000
b100 #
b100 2
b100 8
b100 :
b100 9
1%
#415000
0%
#416000
b11 #
b11 2
b11 8
b11 :
b11 9
1%
#417000
0%
#418000
b10 #
b10 2
b10 8
b10 :
b10 9
1%
#419000
0%
#420000
b1 #
b1 2
b1 8
b1 :
b1 9
1%
#421000
0%
#422000
11
1-
b0 #
b0 2
b0 8
b0 :
b0 9
1%
#423000
0%
#424000
01
0-
b100 "
b100 .
b100 5
b100 ;
b100 <
b1001 #
b1001 2
b1001 8
b1001 :
b1001 9
1%
#425000
0%
#426000
b1000 #
b1000 2
b1000 8
b1000 :
b1000 9
1%
#427000
0%
#428000
b111 #
b111 2
b111 8
b111 :
b111 9
1%
#429000
0%
#430000
b110 #
b110 2
b110 8
b110 :
b110 9
1%
#431000
0%
#432000
b101 #
b101 2
b101 8
b101 :
b101 9
1%
#433000
0%
#434000
b100 #
b100 2
b100 8
b100 :
b100 9
1%
#435000
0%
#436000
b11 #
b11 2
b11 8
b11 :
b11 9
1%
#437000
0%
#438000
b10 #
b10 2
b10 8
b10 :
b10 9
1%
#439000
0%
#440000
b1 #
b1 2
b1 8
b1 :
b1 9
1%
#441000
0%
#442000
11
1-
b0 #
b0 2
b0 8
b0 :
b0 9
1%
#443000
0%
#444000
01
0-
b11 "
b11 .
b11 5
b11 ;
b11 <
b1001 #
b1001 2
b1001 8
b1001 :
b1001 9
1%
#445000
0%
#446000
b1000 #
b1000 2
b1000 8
b1000 :
b1000 9
1%
#447000
0%
#448000
b111 #
b111 2
b111 8
b111 :
b111 9
1%
#449000
0%
#450000
b110 #
b110 2
b110 8
b110 :
b110 9
1%
#451000
0%
#452000
b101 #
b101 2
b101 8
b101 :
b101 9
1%
#453000
0%
#454000
b100 #
b100 2
b100 8
b100 :
b100 9
1%
#455000
0%
#456000
b11 #
b11 2
b11 8
b11 :
b11 9
1%
#457000
0%
#458000
b10 #
b10 2
b10 8
b10 :
b10 9
1%
#459000
0%
#460000
b1 #
b1 2
b1 8
b1 :
b1 9
1%
#461000
0%
#462000
11
1-
b0 #
b0 2
b0 8
b0 :
b0 9
1%
#463000
0%
#464000
01
0-
b10 "
b10 .
b10 5
b10 ;
b10 <
b1001 #
b1001 2
b1001 8
b1001 :
b1001 9
1%
#465000
0%
#466000
b1000 #
b1000 2
b1000 8
b1000 :
b1000 9
1%
#467000
0%
#468000
b111 #
b111 2
b111 8
b111 :
b111 9
1%
#469000
0%
#470000
b110 #
b110 2
b110 8
b110 :
b110 9
1%
#471000
0%
#472000
b101 #
b101 2
b101 8
b101 :
b101 9
1%
#473000
0%
#474000
b100 #
b100 2
b100 8
b100 :
b100 9
1%
#475000
0%
#476000
b11 #
b11 2
b11 8
b11 :
b11 9
1%
#477000
0%
#478000
b10 #
b10 2
b10 8
b10 :
b10 9
1%
#479000
0%
#480000
b1 #
b1 2
b1 8
b1 :
b1 9
1%
#481000
0%
#482000
11
1-
b0 #
b0 2
b0 8
b0 :
b0 9
1%
#483000
0%
#484000
01
0-
b1 "
b1 .
b1 5
b1 ;
b1 <
b1001 #
b1001 2
b1001 8
b1001 :
b1001 9
1%
#485000
0%
#486000
b1000 #
b1000 2
b1000 8
b1000 :
b1000 9
1%
#487000
0%
#488000
b111 #
b111 2
b111 8
b111 :
b111 9
1%
#489000
0%
#490000
b110 #
b110 2
b110 8
b110 :
b110 9
1%
#491000
0%
#492000
b101 #
b101 2
b101 8
b101 :
b101 9
1%
#493000
0%
#494000
b100 #
b100 2
b100 8
b100 :
b100 9
1%
#495000
0%
#496000
b11 #
b11 2
b11 8
b11 :
b11 9
1%
#497000
0%
#498000
b10 #
b10 2
b10 8
b10 :
b10 9
1%
#499000
0%
#500000
b1 #
b1 2
b1 8
b1 :
b1 9
1%
#501000
0%
#502000
11
1-
b0 #
b0 2
b0 8
b0 :
b0 9
1%
#503000
0%
#504000
00
01
1,
0-
b0 "
b0 .
b0 5
b0 ;
b0 <
b1001 #
b1001 2
b1001 8
b1001 :
b1001 9
1%
#505000
0%
#506000
b1000 #
b1000 2
b1000 8
b1000 :
b1000 9
1%
#507000
0%
#508000
b111 #
b111 2
b111 8
b111 :
b111 9
1%
#509000
0%
#510000
b110 #
b110 2
b110 8
b110 :
b110 9
1%
#511000
0%
#512000
b101 #
b101 2
b101 8
b101 :
b101 9
1%
#513000
0%
#514000
b100 #
b100 2
b100 8
b100 :
b100 9
1%
#515000
0%
#516000
b11 #
b11 2
b11 8
b11 :
b11 9
1%
#517000
0%
#518000
b10 #
b10 2
b10 8
b10 :
b10 9
1%
#519000
0%
#520000
b1 #
b1 2
b1 8
b1 :
b1 9
1%
#521000
0%
#522000
10
11
1-
b0 #
b0 2
b0 8
b0 :
b0 9
1%
#523000
0%
